labels/__init__.py
labels/cli.py
labels/exceptions.py
labels/github.py
labels/io.py
labels/log.py
labels/utils.py
labels-20.1.0.dist-info/LICENSE
labels-20.1.0.dist-info/METADATA
labels-20.1.0.dist-info/WHEEL
labels-20.1.0.dist-info/entry_points.txt
labels-20.1.0.dist-info/top_level.txt
labels-20.1.0.dist-info/RECORD
