Metadata-Version: 2.1
Name: labels
Version: 20.1.0
Summary: CLI app for managing GitHub labels for Python 3.6 and newer. 📝
Home-page: https://github.com/hackebrot/labels
Author: Raphael Pierzina
Author-email: raphael@hackebrot.de
Maintainer: Raphael Pierzina
Maintainer-email: raphael@hackebrot.de
License: MIT
Project-URL: Repository, https://github.com/hackebrot/labels
Project-URL: Issues, https://github.com/hackebrot/labels/issues
Keywords: github,command-line
Platform: UNKNOWN
Classifier: Development Status :: 3 - Alpha
Classifier: Intended Audience :: Developers
Classifier: License :: OSI Approved :: MIT License
Classifier: Natural Language :: English
Classifier: Operating System :: OS Independent
Classifier: Programming Language :: Python :: 3 :: Only
Classifier: Programming Language :: Python :: 3.6
Classifier: Programming Language :: Python :: 3.7
Classifier: Programming Language :: Python :: Implementation :: CPython
Classifier: Topic :: Utilities
Requires-Python: >=3.6
